Metadata-Version: 2.1
Name: birdspy
Version: 0.1.0
Summary: Bayesian inference for differentiable simulators.
Home-page: https://github.com/arnauqb/birds
Author: Ayush Chopra and Joel Dyer and Arnau Quera-Bofarull
Author-email: arnauq@protonmail.com
License: MIT License
License-File: LICENSE
